chaosmeter/ChaosMeter.py
chaosmeter/License.py
chaosmeter/__init__.py
chaosmeter/__main__.py
chaosmeter/metrics/CyclomaticComplexity.py
chaosmeter/metrics/Metric.py
chaosmeter/metrics/MutantDensity.py
chaosmeter/metrics/SourceLinesOfCode.py
chaosmeter/metrics/__init__.py
chaosmeter/writers/CSVWriter.py
chaosmeter/writers/ODSWriter.py
chaosmeter/writers/Writer.py
chaosmeter/writers/__init__.py
chaosmeter-0.1.7.dist-info/LICENSE.md
chaosmeter-0.1.7.dist-info/METADATA
chaosmeter-0.1.7.dist-info/WHEEL
chaosmeter-0.1.7.dist-info/entry_points.txt
chaosmeter-0.1.7.dist-info/top_level.txt
chaosmeter-0.1.7.dist-info/RECORD
