Metadata-Version: 2.1
Name: chaosmeter
Version: 0.1.7
Summary: ChaosMeter Complexity Metric Calculator
Home-page: https://chaosmeter.parsai.net/
Author: Ali Parsai
Author-email: ali.parsai@live.com
License: GNU GPLv3
Platform: UNKNOWN
Classifier: Programming Language :: Python :: 3
Classifier: License :: OSI Approved :: GNU General Public License v3 or later (GPLv3+)
Classifier: Operating System :: OS Independent
Requires-Python: >=3.6
Requires-Dist: antlr4-python3-runtime
Requires-Dist: tqdm
Requires-Dist: odfpy
Requires-Dist: littledarwin
